CHANGES.txt
LICENSE.txt
MANIFEST.in
README.rst
setup.py
pyramid_foundation/__init__.py
pyramid_foundation.egg-info/PKG-INFO
pyramid_foundation.egg-info/SOURCES.txt
pyramid_foundation.egg-info/dependency_links.txt
pyramid_foundation.egg-info/entry_points.txt
pyramid_foundation.egg-info/requires.txt
pyramid_foundation.egg-info/top_level.txt
pyramid_foundation/scaffolds/__init__.py
pyramid_foundation/scaffolds/pyramid_foundation_scaffold/+package+/static/config.rb
pyramid_foundation/scaffolds/pyramid_foundation_scaffold/+package+/static/css/+package+.css
pyramid_foundation/scaffolds/pyramid_foundation_scaffold/+package+/static/css/foundation.css
pyramid_foundation/scaffolds/pyramid_foundation_scaffold/+package+/static/css/foundation.min.css
pyramid_foundation/scaffolds/pyramid_foundation_scaffold/+package+/static/css/normalize.css
pyramid_foundation/scaffolds/pyramid_foundation_scaffold/+package+/static/js/foundation.min.js
pyramid_foundation/scaffolds/pyramid_foundation_scaffold/+package+/static/js/foundation/foundation.alerts.js
pyramid_foundation/scaffolds/pyramid_foundation_scaffold/+package+/static/js/foundation/foundation.clearing.js
pyramid_foundation/scaffolds/pyramid_foundation_scaffold/+package+/static/js/foundation/foundation.cookie.js
pyramid_foundation/scaffolds/pyramid_foundation_scaffold/+package+/static/js/foundation/foundation.dropdown.js
pyramid_foundation/scaffolds/pyramid_foundation_scaffold/+package+/static/js/foundation/foundation.forms.js
pyramid_foundation/scaffolds/pyramid_foundation_scaffold/+package+/static/js/foundation/foundation.joyride.js
pyramid_foundation/scaffolds/pyramid_foundation_scaffold/+package+/static/js/foundation/foundation.js
pyramid_foundation/scaffolds/pyramid_foundation_scaffold/+package+/static/js/foundation/foundation.magellan.js
pyramid_foundation/scaffolds/pyramid_foundation_scaffold/+package+/static/js/foundation/foundation.orbit.js
pyramid_foundation/scaffolds/pyramid_foundation_scaffold/+package+/static/js/foundation/foundation.placeholder.js
pyramid_foundation/scaffolds/pyramid_foundation_scaffold/+package+/static/js/foundation/foundation.reveal.js
pyramid_foundation/scaffolds/pyramid_foundation_scaffold/+package+/static/js/foundation/foundation.section.js
