Metadata-Version: 1.0
Name: pyramid-foundation
Version: 0.3.0
Summary: Pyramid scaffold to extend project with Foundation support
Home-page: https://github.com/ppinette/pyramid_foundation
Author: Parker Pinette
Author-email: parker@parkerpinette.com
License: LICENSE.txt
Platform: UNKNOWN
